LICENSE
README.md
setup.py
Escola.egg-info/PKG-INFO
Escola.egg-info/SOURCES.txt
Escola.egg-info/dependency_links.txt
Escola.egg-info/requires.txt
Escola.egg-info/top_level.txt
my_library/Escola.py
my_library/Grade.py
my_library/Lista_profs.py
my_library/__init__.py