Metadata-Version: 2.1
Name: Escola
Version: 0.0.1
Summary: Projeto OO
Home-page: UNKNOWN
Author: Larissa de Jesus Vieira
Author-email: lalasarandi@gmail.com
License: MIT License
Keywords: escola
Platform: UNKNOWN
License-File: LICENSE
